{"properties": [
  {
    "name": "birthday.swagger.contact.name",
    "type": "java.lang.String",
    "description": "A description for 'birthday.swagger.contact.name'"
  },
  {
    "name": "birthday.properties.expiration",
    "type": "java.lang.String",
    "description": "A description for 'birthday.properties.expiration'"
  },
  {
    "name": "birthday.properties.secret_key",
    "type": "java.lang.String",
    "description": "A description for 'birthday.properties.secret_key'"
  },
  {
    "name": "birthday.swagger.contact.url",
    "type": "java.lang.String",
    "description": "A description for 'birthday.swagger.contact.url'"
  },
  {
    "name": "birthday.swagger.contact.email",
    "type": "java.lang.String",
    "description": "A description for 'birthday.swagger.contact.email'"
  },
  {
    "name": "celebrave.properties.secret_key",
    "type": "java.lang.String",
    "description": "A description for 'celebrave.properties.secret_key'"
  },
  {
    "name": "celebrave.properties.expiration",
    "type": "java.lang.String",
    "description": "A description for 'celebrave.properties.expiration'"
  },
  {
    "name": "celebrave.swagger.contact.name",
    "type": "java.lang.String",
    "description": "A description for 'celebrave.swagger.contact.name'"
  },
  {
    "name": "celebrave.swagger.contact.url",
    "type": "java.lang.String",
    "description": "A description for 'celebrave.swagger.contact.url'"
  },
  {
    "name": "celebrave.swagger.contact.email",
    "type": "java.lang.String",
    "description": "A description for 'celebrave.swagger.contact.email'"
  }
]}